{
    "id": "449",
    "name": "砥上裕將",
    "kana": "とがみひろまさ",
    "imgUrl": "None",
    "bornDate": "",
    "deadDate": "",
    "countryId": "108",
    "countryName": "日本",
    "overview": "日本の水墨画家、小説家。福岡県生まれ。",
    "wikipediaUrl": "http://ja.wikipedia.org/wiki/%E7%A0%A5%E4%B8%8A%E8%A3%95%E5%B0%87",
    "awardWinningWorks": {
        "listtitle": [
            "タイトル", "受賞" 
        ],
        "listitem": [
                                            {
                    "key": 0,
                    "value": [
                        { "text": "<a href='../pages/book.htm?id=453'>線は、僕を描く</a>" },
                        { "text": "第59回 <a href='../pages/award.htm?id=8'>メフィスト賞</a>" }
                    ]
                }
                    ]
    }
}